pybobyqa/__init__.py
pybobyqa/controller.py
pybobyqa/diagnostic_info.py
pybobyqa/hessian.py
pybobyqa/model.py
pybobyqa/params.py
pybobyqa/solver.py
pybobyqa/trust_region.py
pybobyqa/util.py
Py_BOBYQA-1.5.0.dist-info/LICENSE.txt
Py_BOBYQA-1.5.0.dist-info/METADATA
Py_BOBYQA-1.5.0.dist-info/WHEEL
Py_BOBYQA-1.5.0.dist-info/top_level.txt
Py_BOBYQA-1.5.0.dist-info/RECORD
