Metadata-Version: 2.1
Name: Py-BOBYQA
Version: 1.5.0
Summary: A flexible derivative-free solver for (bound constrained) general objective minimization
Author-email: Lindon Roberts <lindon.roberts@sydney.edu.au>
Maintainer-email: Lindon Roberts <lindon.roberts@sydney.edu.au>
License: GPL-3.0-or-later
Project-URL: Homepage, https://github.com/numericalalgorithmsgroup/pybobyqa
Project-URL: Download, https://github.com/numericalalgorithmsgroup/pybobyqa/releases/
Project-URL: Bug Tracker, https://github.com/numericalalgorithmsgroup/pybobyqa/issues/
Project-URL: Documentation, https://numericalalgorithmsgroup.github.io/pybobyqa/
Project-URL: Source Code, https://github.com/numericalalgorithmsgroup/pybobyqa
Keywords: mathematics,optimization,derivative free optimization
Classifier: Development Status :: 5 - Production/Stable
Classifier: Environment :: Console
Classifier: Framework :: IPython
Classifier: Framework :: Jupyter
Classifier: Intended Audience :: Science/Research
Classifier: License :: OSI Approved :: GNU General Public License v3 or later (GPLv3+)
Classifier: Operating System :: MacOS
Classifier: Operating System :: Microsoft :: Windows
Classifier: Operating System :: Unix
Classifier: Programming Language :: Python
Classifier: Programming Language :: Python :: 3
Classifier: Programming Language :: Python :: 3.8
Classifier: Programming Language :: Python :: 3.9
Classifier: Programming Language :: Python :: 3.10
Classifier: Programming Language :: Python :: 3.11
Classifier: Programming Language :: Python :: 3.12
Classifier: Topic :: Scientific/Engineering
Classifier: Topic :: Scientific/Engineering :: Mathematics
Requires-Python: >=3.8
License-File: LICENSE.txt
Requires-Dist: setuptools
Requires-Dist: numpy
Requires-Dist: scipy
Requires-Dist: pandas
Provides-Extra: dev
Requires-Dist: pytest; extra == "dev"
Requires-Dist: Sphinx; extra == "dev"
Requires-Dist: sphinx-rtd-theme; extra == "dev"
Provides-Extra: trustregion
Requires-Dist: trustregion>=1.1; extra == "trustregion"
